stacks_featuredlink/__init__.py
stacks_featuredlink/admin.py
stacks_featuredlink/apps.py
stacks_featuredlink/models.py
stacks_featuredlink/serializers.py
stacks_featuredlink/stuff.py
stacks_featuredlink/migrations/0001_initial.py
stacks_featuredlink/migrations/0002_auto_20150421_1930.py
stacks_featuredlink/migrations/0003_auto_20150528_1559.py
stacks_featuredlink/migrations/0004_auto_20150528_1601.py
stacks_featuredlink/migrations/0005_remove_stacksfeaturedlinklist_list_name.py
stacks_featuredlink/migrations/0006_auto_20150529_2033.py
stacks_featuredlink/migrations/0007_stacksfeaturedlink_overline.py
stacks_featuredlink/migrations/__init__.py
stacks_featuredlink/templates/stacks_featuredlink/stacksfeaturedlink/stacksfeaturedlink-button.html
stacks_featuredlink/templates/stacks_featuredlink/stacksfeaturedlinklist/stacksfeaturedlinklist-1up.html
stacks_featuredlink/templates/stacks_featuredlink/stacksfeaturedlinklist/stacksfeaturedlinklist-2up.html
stacks_featuredlink/templates/stacks_featuredlink/stacksfeaturedlinklist/stacksfeaturedlinklist-3up.html
stacks_featuredlink-0.2.dist-info/DESCRIPTION.rst
stacks_featuredlink-0.2.dist-info/LICENSE.txt
stacks_featuredlink-0.2.dist-info/METADATA
stacks_featuredlink-0.2.dist-info/metadata.json
stacks_featuredlink-0.2.dist-info/RECORD
stacks_featuredlink-0.2.dist-info/top_level.txt
stacks_featuredlink-0.2.dist-info/WHEEL
tests/__init__.py
tests/test_settings.py
tests/tests.py
tests/urls.py
